plone.batching-2.0.7-py3.13-nspkg.pth
plone/batching/__init__.py
plone/batching/batch.py
plone/batching/batch_macros.pt
plone/batching/batching.rst
plone/batching/batchnavigation.pt
plone/batching/batchnavigation_bootstrap.pt
plone/batching/browser.py
plone/batching/configure.zcml
plone/batching/interfaces.py
plone/batching/utils.py
plone/batching/tests/__init__.py
plone/batching/tests/test_batching.py
plone_batching-2.0.7.dist-info/METADATA
plone_batching-2.0.7.dist-info/WHEEL
plone_batching-2.0.7.dist-info/entry_points.txt
plone_batching-2.0.7.dist-info/namespace_packages.txt
plone_batching-2.0.7.dist-info/top_level.txt
plone_batching-2.0.7.dist-info/RECORD
